yta_youtube_enhanced/__init__.py
yta_youtube_enhanced/dataclasses.py
yta_youtube_enhanced/enums.py
yta_youtube_enhanced/video.py
yta_youtube_enhanced-0.0.5.dist-info/LICENSE
yta_youtube_enhanced-0.0.5.dist-info/METADATA
yta_youtube_enhanced-0.0.5.dist-info/WHEEL
yta_youtube_enhanced-0.0.5.dist-info/RECORD
