Metadata-Version: 2.3
Name: yta-youtube-enhanced
Version: 0.0.5
Summary: 
Author: danialcala94
Author-email: danielalcalavalera@gmail.com
Requires-Python: ==3.9
Classifier: Programming Language :: Python :: 3
Classifier: Programming Language :: Python :: 3.9
Requires-Dist: yta_ai_utils (>=0.0.11,<0.1.0)
Requires-Dist: yta_general_utils (>=0.0.250,<0.1.0)
Requires-Dist: yta_youtube (>=0.0.11,<0.1.0)
